[{"name":"file_tree_view","qualifiedName":"file_tree_view","href":"file_tree_view/file_tree_view-library.html","kind":9,"packageRank":0,"desc":""},{"name":"DirectoryTreeStateNotifier","qualifiedName":"file_tree_view.DirectoryTreeStateNotifier","href":"file_tree_view/DirectoryTreeStateNotifier-class.html","kind":3,"packageRank":0,"desc":"Manages the state of the directory tree, handling folder expansion and file operations.","enclosedBy":{"name":"file_tree_view","kind":9,"href":"file_tree_view/file_tree_view-library.html"}},{"name":"DirectoryTreeStateNotifier","qualifiedName":"file_tree_view.DirectoryTreeStateNotifier.DirectoryTreeStateNotifier","href":"file_tree_view/DirectoryTreeStateNotifier/DirectoryTreeStateNotifier.html","kind":2,"packageRank":0,"desc":"","enclosedBy":{"name":"DirectoryTreeStateNotifier","kind":3,"href":"file_tree_view/DirectoryTreeStateNotifier-class.html"}},{"name":"isFolderCreation","qualifiedName":"file_tree_view.DirectoryTreeStateNotifier.isFolderCreation","href":"file_tree_view/DirectoryTreeStateNotifier/isFolderCreation.html","kind":16,"overriddenDepth":0,"packageRank":0,"desc":"Flag to determine if new entry is a folder","enclosedBy":{"name":"DirectoryTreeStateNotifier","kind":3,"href":"file_tree_view/DirectoryTreeStateNotifier-class.html"}},{"name":"isUnfolded","qualifiedName":"file_tree_view.DirectoryTreeStateNotifier.isUnfolded","href":"file_tree_view/DirectoryTreeStateNotifier/isUnfolded.html","kind":10,"overriddenDepth":0,"packageRank":0,"desc":"Checks if a folder is expanded or collapsed","enclosedBy":{"name":"DirectoryTreeStateNotifier","kind":3,"href":"file_tree_view/DirectoryTreeStateNotifier-class.html"}},{"name":"newEntryPath","qualifiedName":"file_tree_view.DirectoryTreeStateNotifier.newEntryPath","href":"file_tree_view/DirectoryTreeStateNotifier/newEntryPath.html","kind":16,"overriddenDepth":0,"packageRank":0,"desc":"Path of the new entry being created","enclosedBy":{"name":"DirectoryTreeStateNotifier","kind":3,"href":"file_tree_view/DirectoryTreeStateNotifier-class.html"}},{"name":"startCreating","qualifiedName":"file_tree_view.DirectoryTreeStateNotifier.startCreating","href":"file_tree_view/DirectoryTreeStateNotifier/startCreating.html","kind":10,"overriddenDepth":0,"packageRank":0,"desc":"Starts the creation process of a new folder or file","enclosedBy":{"name":"DirectoryTreeStateNotifier","kind":3,"href":"file_tree_view/DirectoryTreeStateNotifier-class.html"}},{"name":"stopCreating","qualifiedName":"file_tree_view.DirectoryTreeStateNotifier.stopCreating","href":"file_tree_view/DirectoryTreeStateNotifier/stopCreating.html","kind":10,"overriddenDepth":0,"packageRank":0,"desc":"Stops the creation process and clears the state","enclosedBy":{"name":"DirectoryTreeStateNotifier","kind":3,"href":"file_tree_view/DirectoryTreeStateNotifier-class.html"}},{"name":"toggleFolder","qualifiedName":"file_tree_view.DirectoryTreeStateNotifier.toggleFolder","href":"file_tree_view/DirectoryTreeStateNotifier/toggleFolder.html","kind":10,"overriddenDepth":0,"packageRank":0,"desc":"Toggles folder expansion/collapse state","enclosedBy":{"name":"DirectoryTreeStateNotifier","kind":3,"href":"file_tree_view/DirectoryTreeStateNotifier-class.html"}},{"name":"watchDirectory","qualifiedName":"file_tree_view.DirectoryTreeStateNotifier.watchDirectory","href":"file_tree_view/DirectoryTreeStateNotifier/watchDirectory.html","kind":10,"overriddenDepth":0,"packageRank":0,"desc":"Watches the given directory for changes and updates the UI accordingly","enclosedBy":{"name":"DirectoryTreeStateNotifier","kind":3,"href":"file_tree_view/DirectoryTreeStateNotifier-class.html"}},{"name":"DirectoryTreeStateProvider","qualifiedName":"file_tree_view.DirectoryTreeStateProvider","href":"file_tree_view/DirectoryTreeStateProvider-class.html","kind":3,"packageRank":0,"desc":"A provider that supplies DirectoryTreeStateNotifier to its descendants in the widget tree.","enclosedBy":{"name":"file_tree_view","kind":9,"href":"file_tree_view/file_tree_view-library.html"}},{"name":"DirectoryTreeStateProvider","qualifiedName":"file_tree_view.DirectoryTreeStateProvider.DirectoryTreeStateProvider","href":"file_tree_view/DirectoryTreeStateProvider/DirectoryTreeStateProvider.html","kind":2,"packageRank":0,"desc":"Constructs a DirectoryTreeStateProvider with the given notifier and child widget.","enclosedBy":{"name":"DirectoryTreeStateProvider","kind":3,"href":"file_tree_view/DirectoryTreeStateProvider-class.html"}},{"name":"of","qualifiedName":"file_tree_view.DirectoryTreeStateProvider.of","href":"file_tree_view/DirectoryTreeStateProvider/of.html","kind":10,"overriddenDepth":0,"packageRank":0,"desc":"Accesses the DirectoryTreeStateNotifier in the widget tree.","enclosedBy":{"name":"DirectoryTreeStateProvider","kind":3,"href":"file_tree_view/DirectoryTreeStateProvider-class.html"}},{"name":"DirectoryTreeViewer","qualifiedName":"file_tree_view.DirectoryTreeViewer","href":"file_tree_view/DirectoryTreeViewer-class.html","kind":3,"packageRank":0,"desc":"","enclosedBy":{"name":"file_tree_view","kind":9,"href":"file_tree_view/file_tree_view-library.html"}},{"name":"DirectoryTreeViewer","qualifiedName":"file_tree_view.DirectoryTreeViewer.DirectoryTreeViewer","href":"file_tree_view/DirectoryTreeViewer/DirectoryTreeViewer.html","kind":2,"packageRank":0,"desc":"Constructs a DirectoryTreeViewer with the given properties.","enclosedBy":{"name":"DirectoryTreeViewer","kind":3,"href":"file_tree_view/DirectoryTreeViewer-class.html"}},{"name":"build","qualifiedName":"file_tree_view.DirectoryTreeViewer.build","href":"file_tree_view/DirectoryTreeViewer/build.html","kind":10,"overriddenDepth":1,"packageRank":0,"desc":"Describes the part of the user interface represented by this widget.","enclosedBy":{"name":"DirectoryTreeViewer","kind":3,"href":"file_tree_view/DirectoryTreeViewer-class.html"}},{"name":"editingFieldStyle","qualifiedName":"file_tree_view.DirectoryTreeViewer.editingFieldStyle","href":"file_tree_view/DirectoryTreeViewer/editingFieldStyle.html","kind":16,"overriddenDepth":0,"packageRank":0,"desc":"Custom styling for text editing field.","enclosedBy":{"name":"DirectoryTreeViewer","kind":3,"href":"file_tree_view/DirectoryTreeViewer-class.html"}},{"name":"enableCreateFileOption","qualifiedName":"file_tree_view.DirectoryTreeViewer.enableCreateFileOption","href":"file_tree_view/DirectoryTreeViewer/enableCreateFileOption.html","kind":16,"overriddenDepth":0,"packageRank":0,"desc":"Enables file creation option","enclosedBy":{"name":"DirectoryTreeViewer","kind":3,"href":"file_tree_view/DirectoryTreeViewer-class.html"}},{"name":"enableCreateFolderOption","qualifiedName":"file_tree_view.DirectoryTreeViewer.enableCreateFolderOption","href":"file_tree_view/DirectoryTreeViewer/enableCreateFolderOption.html","kind":16,"overriddenDepth":0,"packageRank":0,"desc":"Enables folder creation option","enclosedBy":{"name":"DirectoryTreeViewer","kind":3,"href":"file_tree_view/DirectoryTreeViewer-class.html"}},{"name":"enableDeleteFileOption","qualifiedName":"file_tree_view.DirectoryTreeViewer.enableDeleteFileOption","href":"file_tree_view/DirectoryTreeViewer/enableDeleteFileOption.html","kind":16,"overriddenDepth":0,"packageRank":0,"desc":"Enables file deletion option","enclosedBy":{"name":"DirectoryTreeViewer","kind":3,"href":"file_tree_view/DirectoryTreeViewer-class.html"}},{"name":"enableDeleteFolderOption","qualifiedName":"file_tree_view.DirectoryTreeViewer.enableDeleteFolderOption","href":"file_tree_view/DirectoryTreeViewer/enableDeleteFolderOption.html","kind":16,"overriddenDepth":0,"packageRank":0,"desc":"Enables folder deletion option","enclosedBy":{"name":"DirectoryTreeViewer","kind":3,"href":"file_tree_view/DirectoryTreeViewer-class.html"}},{"name":"fileActions","qualifiedName":"file_tree_view.DirectoryTreeViewer.fileActions","href":"file_tree_view/DirectoryTreeViewer/fileActions.html","kind":16,"overriddenDepth":0,"packageRank":0,"desc":"Additional file action widgets","enclosedBy":{"name":"DirectoryTreeViewer","kind":3,"href":"file_tree_view/DirectoryTreeViewer-class.html"}},{"name":"fileIconBuilder","qualifiedName":"file_tree_view.DirectoryTreeViewer.fileIconBuilder","href":"file_tree_view/DirectoryTreeViewer/fileIconBuilder.html","kind":16,"overriddenDepth":0,"packageRank":0,"desc":"A function that returns a custom file icon based on the file extension.","enclosedBy":{"name":"DirectoryTreeViewer","kind":3,"href":"file_tree_view/DirectoryTreeViewer-class.html"}},{"name":"fileStyle","qualifiedName":"file_tree_view.DirectoryTreeViewer.fileStyle","href":"file_tree_view/DirectoryTreeViewer/fileStyle.html","kind":16,"overriddenDepth":0,"packageRank":0,"desc":"Customizable file styling","enclosedBy":{"name":"DirectoryTreeViewer","kind":3,"href":"file_tree_view/DirectoryTreeViewer-class.html"}},{"name":"folderActions","qualifiedName":"file_tree_view.DirectoryTreeViewer.folderActions","href":"file_tree_view/DirectoryTreeViewer/folderActions.html","kind":16,"overriddenDepth":0,"packageRank":0,"desc":"Additional folder action widgets","enclosedBy":{"name":"DirectoryTreeViewer","kind":3,"href":"file_tree_view/DirectoryTreeViewer-class.html"}},{"name":"folderStyle","qualifiedName":"file_tree_view.DirectoryTreeViewer.folderStyle","href":"file_tree_view/DirectoryTreeViewer/folderStyle.html","kind":16,"overriddenDepth":0,"packageRank":0,"desc":"Customizable folder styling","enclosedBy":{"name":"DirectoryTreeViewer","kind":3,"href":"file_tree_view/DirectoryTreeViewer-class.html"}},{"name":"isUnfoldedFirst","qualifiedName":"file_tree_view.DirectoryTreeViewer.isUnfoldedFirst","href":"file_tree_view/DirectoryTreeViewer/isUnfoldedFirst.html","kind":16,"overriddenDepth":0,"packageRank":0,"desc":"Initial state of the DirectoryTreeViewer.\nisUnfoldedFirst = true by defualt","enclosedBy":{"name":"DirectoryTreeViewer","kind":3,"href":"file_tree_view/DirectoryTreeViewer-class.html"}},{"name":"onFileTap","qualifiedName":"file_tree_view.DirectoryTreeViewer.onFileTap","href":"file_tree_view/DirectoryTreeViewer/onFileTap.html","kind":16,"overriddenDepth":0,"packageRank":0,"desc":"Callback function when a file is tapped. Accepts a File as parameter.","enclosedBy":{"name":"DirectoryTreeViewer","kind":3,"href":"file_tree_view/DirectoryTreeViewer-class.html"}},{"name":"rootPath","qualifiedName":"file_tree_view.DirectoryTreeViewer.rootPath","href":"file_tree_view/DirectoryTreeViewer/rootPath.html","kind":16,"overriddenDepth":0,"packageRank":0,"desc":"The root path of the directory to display.","enclosedBy":{"name":"DirectoryTreeViewer","kind":3,"href":"file_tree_view/DirectoryTreeViewer-class.html"}},{"name":"FoldableDirectoryTree","qualifiedName":"file_tree_view.FoldableDirectoryTree","href":"file_tree_view/FoldableDirectoryTree-class.html","kind":3,"packageRank":0,"desc":"A widget that displays a foldable directory tree, showing files and subdirectories.","enclosedBy":{"name":"file_tree_view","kind":9,"href":"file_tree_view/file_tree_view-library.html"}},{"name":"FoldableDirectoryTree","qualifiedName":"file_tree_view.FoldableDirectoryTree.FoldableDirectoryTree","href":"file_tree_view/FoldableDirectoryTree/FoldableDirectoryTree.html","kind":2,"packageRank":0,"desc":"","enclosedBy":{"name":"FoldableDirectoryTree","kind":3,"href":"file_tree_view/FoldableDirectoryTree-class.html"}},{"name":"createState","qualifiedName":"file_tree_view.FoldableDirectoryTree.createState","href":"file_tree_view/FoldableDirectoryTree/createState.html","kind":10,"overriddenDepth":1,"packageRank":0,"desc":"Creates the mutable state for this widget at a given location in the tree.","enclosedBy":{"name":"FoldableDirectoryTree","kind":3,"href":"file_tree_view/FoldableDirectoryTree-class.html"}},{"name":"editingFieldStyle","qualifiedName":"file_tree_view.FoldableDirectoryTree.editingFieldStyle","href":"file_tree_view/FoldableDirectoryTree/editingFieldStyle.html","kind":16,"overriddenDepth":0,"packageRank":0,"desc":"","enclosedBy":{"name":"FoldableDirectoryTree","kind":3,"href":"file_tree_view/FoldableDirectoryTree-class.html"}},{"name":"enableCreateFileOption","qualifiedName":"file_tree_view.FoldableDirectoryTree.enableCreateFileOption","href":"file_tree_view/FoldableDirectoryTree/enableCreateFileOption.html","kind":16,"overriddenDepth":0,"packageRank":0,"desc":"","enclosedBy":{"name":"FoldableDirectoryTree","kind":3,"href":"file_tree_view/FoldableDirectoryTree-class.html"}},{"name":"enableCreateFolderOption","qualifiedName":"file_tree_view.FoldableDirectoryTree.enableCreateFolderOption","href":"file_tree_view/FoldableDirectoryTree/enableCreateFolderOption.html","kind":16,"overriddenDepth":0,"packageRank":0,"desc":"","enclosedBy":{"name":"FoldableDirectoryTree","kind":3,"href":"file_tree_view/FoldableDirectoryTree-class.html"}},{"name":"enableDeleteFileOption","qualifiedName":"file_tree_view.FoldableDirectoryTree.enableDeleteFileOption","href":"file_tree_view/FoldableDirectoryTree/enableDeleteFileOption.html","kind":16,"overriddenDepth":0,"packageRank":0,"desc":"","enclosedBy":{"name":"FoldableDirectoryTree","kind":3,"href":"file_tree_view/FoldableDirectoryTree-class.html"}},{"name":"enableDeleteFolderOption","qualifiedName":"file_tree_view.FoldableDirectoryTree.enableDeleteFolderOption","href":"file_tree_view/FoldableDirectoryTree/enableDeleteFolderOption.html","kind":16,"overriddenDepth":0,"packageRank":0,"desc":"","enclosedBy":{"name":"FoldableDirectoryTree","kind":3,"href":"file_tree_view/FoldableDirectoryTree-class.html"}},{"name":"fileActions","qualifiedName":"file_tree_view.FoldableDirectoryTree.fileActions","href":"file_tree_view/FoldableDirectoryTree/fileActions.html","kind":16,"overriddenDepth":0,"packageRank":0,"desc":"","enclosedBy":{"name":"FoldableDirectoryTree","kind":3,"href":"file_tree_view/FoldableDirectoryTree-class.html"}},{"name":"fileIconBuilder","qualifiedName":"file_tree_view.FoldableDirectoryTree.fileIconBuilder","href":"file_tree_view/FoldableDirectoryTree/fileIconBuilder.html","kind":16,"overriddenDepth":0,"packageRank":0,"desc":"","enclosedBy":{"name":"FoldableDirectoryTree","kind":3,"href":"file_tree_view/FoldableDirectoryTree-class.html"}},{"name":"fileStyle","qualifiedName":"file_tree_view.FoldableDirectoryTree.fileStyle","href":"file_tree_view/FoldableDirectoryTree/fileStyle.html","kind":16,"overriddenDepth":0,"packageRank":0,"desc":"","enclosedBy":{"name":"FoldableDirectoryTree","kind":3,"href":"file_tree_view/FoldableDirectoryTree-class.html"}},{"name":"folderActions","qualifiedName":"file_tree_view.FoldableDirectoryTree.folderActions","href":"file_tree_view/FoldableDirectoryTree/folderActions.html","kind":16,"overriddenDepth":0,"packageRank":0,"desc":"","enclosedBy":{"name":"FoldableDirectoryTree","kind":3,"href":"file_tree_view/FoldableDirectoryTree-class.html"}},{"name":"folderStyle","qualifiedName":"file_tree_view.FoldableDirectoryTree.folderStyle","href":"file_tree_view/FoldableDirectoryTree/folderStyle.html","kind":16,"overriddenDepth":0,"packageRank":0,"desc":"","enclosedBy":{"name":"FoldableDirectoryTree","kind":3,"href":"file_tree_view/FoldableDirectoryTree-class.html"}},{"name":"onFileTap","qualifiedName":"file_tree_view.FoldableDirectoryTree.onFileTap","href":"file_tree_view/FoldableDirectoryTree/onFileTap.html","kind":16,"overriddenDepth":0,"packageRank":0,"desc":"","enclosedBy":{"name":"FoldableDirectoryTree","kind":3,"href":"file_tree_view/FoldableDirectoryTree-class.html"}},{"name":"rootPath","qualifiedName":"file_tree_view.FoldableDirectoryTree.rootPath","href":"file_tree_view/FoldableDirectoryTree/rootPath.html","kind":16,"overriddenDepth":0,"packageRank":0,"desc":"","enclosedBy":{"name":"FoldableDirectoryTree","kind":3,"href":"file_tree_view/FoldableDirectoryTree-class.html"}},{"name":"currentDir","qualifiedName":"file_tree_view.currentDir","href":"file_tree_view/currentDir.html","kind":20,"packageRank":0,"desc":"","enclosedBy":{"name":"file_tree_view","kind":9,"href":"file_tree_view/file_tree_view-library.html"}},{"name":"isParentOpen","qualifiedName":"file_tree_view.isParentOpen","href":"file_tree_view/isParentOpen.html","kind":20,"packageRank":0,"desc":"","enclosedBy":{"name":"file_tree_view","kind":9,"href":"file_tree_view/file_tree_view-library.html"}},{"name":"style","qualifiedName":"style","href":"style/style-library.html","kind":9,"packageRank":0,"desc":""},{"name":"EditingFieldStyle","qualifiedName":"style.EditingFieldStyle","href":"style/EditingFieldStyle-class.html","kind":3,"packageRank":0,"desc":"","enclosedBy":{"name":"style","kind":9,"href":"style/style-library.html"}},{"name":"EditingFieldStyle","qualifiedName":"style.EditingFieldStyle.EditingFieldStyle","href":"style/EditingFieldStyle/EditingFieldStyle.html","kind":2,"packageRank":0,"desc":"","enclosedBy":{"name":"EditingFieldStyle","kind":3,"href":"style/EditingFieldStyle-class.html"}},{"name":"cancelIcon","qualifiedName":"style.EditingFieldStyle.cancelIcon","href":"style/EditingFieldStyle/cancelIcon.html","kind":16,"overriddenDepth":0,"packageRank":0,"desc":"Icon for cancel button.","enclosedBy":{"name":"EditingFieldStyle","kind":3,"href":"style/EditingFieldStyle-class.html"}},{"name":"cursorColor","qualifiedName":"style.EditingFieldStyle.cursorColor","href":"style/EditingFieldStyle/cursorColor.html","kind":16,"overriddenDepth":0,"packageRank":0,"desc":"Cursor color.","enclosedBy":{"name":"EditingFieldStyle","kind":3,"href":"style/EditingFieldStyle-class.html"}},{"name":"cursorHeight","qualifiedName":"style.EditingFieldStyle.cursorHeight","href":"style/EditingFieldStyle/cursorHeight.html","kind":16,"overriddenDepth":0,"packageRank":0,"desc":"Height of the cursor.","enclosedBy":{"name":"EditingFieldStyle","kind":3,"href":"style/EditingFieldStyle-class.html"}},{"name":"cursorRadius","qualifiedName":"style.EditingFieldStyle.cursorRadius","href":"style/EditingFieldStyle/cursorRadius.html","kind":16,"overriddenDepth":0,"packageRank":0,"desc":"Cursor radius.","enclosedBy":{"name":"EditingFieldStyle","kind":3,"href":"style/EditingFieldStyle-class.html"}},{"name":"cursorWidth","qualifiedName":"style.EditingFieldStyle.cursorWidth","href":"style/EditingFieldStyle/cursorWidth.html","kind":16,"overriddenDepth":0,"packageRank":0,"desc":"Width of the cursor.","enclosedBy":{"name":"EditingFieldStyle","kind":3,"href":"style/EditingFieldStyle-class.html"}},{"name":"doneIcon","qualifiedName":"style.EditingFieldStyle.doneIcon","href":"style/EditingFieldStyle/doneIcon.html","kind":16,"overriddenDepth":0,"packageRank":0,"desc":"Icon for done button.","enclosedBy":{"name":"EditingFieldStyle","kind":3,"href":"style/EditingFieldStyle-class.html"}},{"name":"fileIcon","qualifiedName":"style.EditingFieldStyle.fileIcon","href":"style/EditingFieldStyle/fileIcon.html","kind":16,"overriddenDepth":0,"packageRank":0,"desc":"Leading icon/widget displayed while creating new file.","enclosedBy":{"name":"EditingFieldStyle","kind":3,"href":"style/EditingFieldStyle-class.html"}},{"name":"folderIcon","qualifiedName":"style.EditingFieldStyle.folderIcon","href":"style/EditingFieldStyle/folderIcon.html","kind":16,"overriddenDepth":0,"packageRank":0,"desc":"Leading icon/widget displayed while creating new folder.","enclosedBy":{"name":"EditingFieldStyle","kind":3,"href":"style/EditingFieldStyle-class.html"}},{"name":"textFieldHeight","qualifiedName":"style.EditingFieldStyle.textFieldHeight","href":"style/EditingFieldStyle/textFieldHeight.html","kind":16,"overriddenDepth":0,"packageRank":0,"desc":"Height of the text field.","enclosedBy":{"name":"EditingFieldStyle","kind":3,"href":"style/EditingFieldStyle-class.html"}},{"name":"textFieldWidth","qualifiedName":"style.EditingFieldStyle.textFieldWidth","href":"style/EditingFieldStyle/textFieldWidth.html","kind":16,"overriddenDepth":0,"packageRank":0,"desc":"Width of the text field.","enclosedBy":{"name":"EditingFieldStyle","kind":3,"href":"style/EditingFieldStyle-class.html"}},{"name":"textStyle","qualifiedName":"style.EditingFieldStyle.textStyle","href":"style/EditingFieldStyle/textStyle.html","kind":16,"overriddenDepth":0,"packageRank":0,"desc":"TextStyle for text in the text filed.","enclosedBy":{"name":"EditingFieldStyle","kind":3,"href":"style/EditingFieldStyle-class.html"}},{"name":"textfieldDecoration","qualifiedName":"style.EditingFieldStyle.textfieldDecoration","href":"style/EditingFieldStyle/textfieldDecoration.html","kind":16,"overriddenDepth":0,"packageRank":0,"desc":"InputDecoration for TextField which appears while creating new file/folder.","enclosedBy":{"name":"EditingFieldStyle","kind":3,"href":"style/EditingFieldStyle-class.html"}},{"name":"verticalTextAlign","qualifiedName":"style.EditingFieldStyle.verticalTextAlign","href":"style/EditingFieldStyle/verticalTextAlign.html","kind":16,"overriddenDepth":0,"packageRank":0,"desc":"Text (Cursor) vertical alignment","enclosedBy":{"name":"EditingFieldStyle","kind":3,"href":"style/EditingFieldStyle-class.html"}},{"name":"FileStyle","qualifiedName":"style.FileStyle","href":"style/FileStyle-class.html","kind":3,"packageRank":0,"desc":"Defines customizable styling options for file elements in the directory tree.","enclosedBy":{"name":"style","kind":9,"href":"style/style-library.html"}},{"name":"FileStyle","qualifiedName":"style.FileStyle.FileStyle","href":"style/FileStyle/FileStyle.html","kind":2,"packageRank":0,"desc":"Constructs a FileStyle with customizable icons and text styles.","enclosedBy":{"name":"FileStyle","kind":3,"href":"style/FileStyle-class.html"}},{"name":"fileIcon","qualifiedName":"style.FileStyle.fileIcon","href":"style/FileStyle/fileIcon.html","kind":16,"overriddenDepth":0,"packageRank":0,"desc":"Default file icon.\nApplied when no custom icon is provided via fileIconBuilder.","enclosedBy":{"name":"FileStyle","kind":3,"href":"style/FileStyle-class.html"}},{"name":"fileNameStyle","qualifiedName":"style.FileStyle.fileNameStyle","href":"style/FileStyle/fileNameStyle.html","kind":16,"overriddenDepth":0,"packageRank":0,"desc":"TextStyle for file tile title.","enclosedBy":{"name":"FileStyle","kind":3,"href":"style/FileStyle-class.html"}},{"name":"iconForDeleteFile","qualifiedName":"style.FileStyle.iconForDeleteFile","href":"style/FileStyle/iconForDeleteFile.html","kind":16,"overriddenDepth":0,"packageRank":0,"desc":"Icon for delete button if it is enabled.","enclosedBy":{"name":"FileStyle","kind":3,"href":"style/FileStyle-class.html"}},{"name":"FolderStyle","qualifiedName":"style.FolderStyle","href":"style/FolderStyle-class.html","kind":3,"packageRank":0,"desc":"Defines customizable styling options for folder elements in the directory tree.","enclosedBy":{"name":"style","kind":9,"href":"style/style-library.html"}},{"name":"FolderStyle","qualifiedName":"style.FolderStyle.FolderStyle","href":"style/FolderStyle/FolderStyle.html","kind":2,"packageRank":0,"desc":"Constructs a FolderStyle with customizable icons and text styles.","enclosedBy":{"name":"FolderStyle","kind":3,"href":"style/FolderStyle-class.html"}},{"name":"folderClosedicon","qualifiedName":"style.FolderStyle.folderClosedicon","href":"style/FolderStyle/folderClosedicon.html","kind":16,"overriddenDepth":0,"packageRank":0,"desc":"Icon displayed when the folder is closed.","enclosedBy":{"name":"FolderStyle","kind":3,"href":"style/FolderStyle-class.html"}},{"name":"folderNameStyle","qualifiedName":"style.FolderStyle.folderNameStyle","href":"style/FolderStyle/folderNameStyle.html","kind":16,"overriddenDepth":0,"packageRank":0,"desc":"Text style applied to folder names.","enclosedBy":{"name":"FolderStyle","kind":3,"href":"style/FolderStyle-class.html"}},{"name":"folderOpenedicon","qualifiedName":"style.FolderStyle.folderOpenedicon","href":"style/FolderStyle/folderOpenedicon.html","kind":16,"overriddenDepth":0,"packageRank":0,"desc":"Icon displayed when the folder is opened.","enclosedBy":{"name":"FolderStyle","kind":3,"href":"style/FolderStyle-class.html"}},{"name":"iconForCreateFile","qualifiedName":"style.FolderStyle.iconForCreateFile","href":"style/FolderStyle/iconForCreateFile.html","kind":16,"overriddenDepth":0,"packageRank":0,"desc":"Icon used for the \"create new file\" action within a folder.","enclosedBy":{"name":"FolderStyle","kind":3,"href":"style/FolderStyle-class.html"}},{"name":"iconForCreateFolder","qualifiedName":"style.FolderStyle.iconForCreateFolder","href":"style/FolderStyle/iconForCreateFolder.html","kind":16,"overriddenDepth":0,"packageRank":0,"desc":"Icon used for the \"create new folder\" action.","enclosedBy":{"name":"FolderStyle","kind":3,"href":"style/FolderStyle-class.html"}},{"name":"iconForDeleteFolder","qualifiedName":"style.FolderStyle.iconForDeleteFolder","href":"style/FolderStyle/iconForDeleteFolder.html","kind":16,"overriddenDepth":0,"packageRank":0,"desc":"Icon used for the \"delete folder\" action.","enclosedBy":{"name":"FolderStyle","kind":3,"href":"style/FolderStyle-class.html"}},{"name":"itemGap","qualifiedName":"style.FolderStyle.itemGap","href":"style/FolderStyle/itemGap.html","kind":16,"overriddenDepth":0,"packageRank":0,"desc":"Gap between items.","enclosedBy":{"name":"FolderStyle","kind":3,"href":"style/FolderStyle-class.html"}},{"name":"rootFolderClosedIcon","qualifiedName":"style.FolderStyle.rootFolderClosedIcon","href":"style/FolderStyle/rootFolderClosedIcon.html","kind":16,"overriddenDepth":0,"packageRank":0,"desc":"Icon for root folder closed state.","enclosedBy":{"name":"FolderStyle","kind":3,"href":"style/FolderStyle-class.html"}},{"name":"rootFolderOpenedIcon","qualifiedName":"style.FolderStyle.rootFolderOpenedIcon","href":"style/FolderStyle/rootFolderOpenedIcon.html","kind":16,"overriddenDepth":0,"packageRank":0,"desc":"Icon for root folder open state.","enclosedBy":{"name":"FolderStyle","kind":3,"href":"style/FolderStyle-class.html"}}]
